[
  {
    "timestamp_ms": 591,
    "action": {
      "ToggleCell": {
        "x": 21,
        "y": 28
      }
    }
  },
  {
    "timestamp_ms": 1407,
    "action": {
      "SetBlocked": {
        "x": 12,
        "y": 33
      }
    }
  },
  {
    "timestamp_ms": 1491,
    "action": {
      "SetBlocked": {
        "x": 9,
        "y": 29
      }
    }
  },
  {
    "timestamp_ms": 1507,
    "action": {
      "SetBlocked": {
        "x": 8,
        "y": 27
      }
    }
  },
  {
    "timestamp_ms": 1524,
    "action": {
      "SetBlocked": {
        "x": 6,
        "y": 25
      }
    }
  },
  {
    "timestamp_ms": 1541,
    "action": {
      "SetBlocked": {
        "x": 6,
        "y": 23
      }
    }
  },
  {
    "timestamp_ms": 1557,
    "action": {
      "SetBlocked": {
        "x": 5,
        "y": 21
      }
    }
  },
  {
    "timestamp_ms": 1574,
    "action": {
      "SetBlocked": {
        "x": 5,
        "y": 20
      }
    }
  },
  {
    "timestamp_ms": 1591,
    "action": {
      "SetBlocked": {
        "x": 5,
        "y": 19
      }
    }
  },
  {
    "timestamp_ms": 1607,
    "action": {
      "SetBlocked": {
        "x": 5,
        "y": 18
      }
    }
  },
  {
    "timestamp_ms": 1624,
    "action": {
      "SetBlocked": {
        "x": 5,
        "y": 17
      }
    }
  },
  {
    "timestamp_ms": 1641,
    "action": {
      "SetBlocked": {
        "x": 5,
        "y": 16
      }
    }
  },
  {
    "timestamp_ms": 1657,
    "action": {
      "SetBlocked": {
        "x": 5,
        "y": 15
      }
    }
  },
  {
    "timestamp_ms": 1674,
    "action": {
      "SetBlocked": {
        "x": 6,
        "y": 14
      }
    }
  },
  {
    "timestamp_ms": 1691,
    "action": {
      "SetBlocked": {
        "x": 7,
        "y": 13
      }
    }
  },
  {
    "timestamp_ms": 1707,
    "action": {
      "SetBlocked": {
        "x": 9,
        "y": 12
      }
    }
  },
  {
    "timestamp_ms": 1724,
    "action": {
      "SetBlocked": {
        "x": 11,
        "y": 11
      }
    }
  },
  {
    "timestamp_ms": 1741,
    "action": {
      "SetBlocked": {
        "x": 12,
        "y": 10
      }
    }
  },
  {
    "timestamp_ms": 1758,
    "action": {
      "SetBlocked": {
        "x": 14,
        "y": 10
      }
    }
  },
  {
    "timestamp_ms": 1774,
    "action": {
      "SetBlocked": {
        "x": 16,
        "y": 9
      }
    }
  },
  {
    "timestamp_ms": 1791,
    "action": {
      "SetBlocked": {
        "x": 17,
        "y": 9
      }
    }
  },
  {
    "timestamp_ms": 1807,
    "action": {
      "SetBlocked": {
        "x": 18,
        "y": 8
      }
    }
  },
  {
    "timestamp_ms": 1824,
    "action": {
      "SetBlocked": {
        "x": 20,
        "y": 8
      }
    }
  },
  {
    "timestamp_ms": 1857,
    "action": {
      "SetBlocked": {
        "x": 21,
        "y": 7
      }
    }
  },
  {
    "timestamp_ms": 1874,
    "action": {
      "SetBlocked": {
        "x": 23,
        "y": 7
      }
    }
  },
  {
    "timestamp_ms": 1907,
    "action": {
      "SetBlocked": {
        "x": 24,
        "y": 7
      }
    }
  },
  {
    "timestamp_ms": 1924,
    "action": {
      "SetBlocked": {
        "x": 25,
        "y": 7
      }
    }
  },
  {
    "timestamp_ms": 1941,
    "action": {
      "SetBlocked": {
        "x": 26,
        "y": 7
      }
    }
  },
  {
    "timestamp_ms": 1974,
    "action": {
      "SetBlocked": {
        "x": 27,
        "y": 8
      }
    }
  },
  {
    "timestamp_ms": 1991,
    "action": {
      "SetBlocked": {
        "x": 28,
        "y": 8
      }
    }
  },
  {
    "timestamp_ms": 2157,
    "action": {
      "SetBlocked": {
        "x": 30,
        "y": 11
      }
    }
  },
  {
    "timestamp_ms": 2174,
    "action": {
      "SetBlocked": {
        "x": 32,
        "y": 14
      }
    }
  },
  {
    "timestamp_ms": 2191,
    "action": {
      "SetBlocked": {
        "x": 33,
        "y": 16
      }
    }
  },
  {
    "timestamp_ms": 2207,
    "action": {
      "SetBlocked": {
        "x": 34,
        "y": 18
      }
    }
  },
  {
    "timestamp_ms": 2224,
    "action": {
      "SetBlocked": {
        "x": 35,
        "y": 20
      }
    }
  },
  {
    "timestamp_ms": 2324,
    "action": {
      "SetBlocked": {
        "x": 35,
        "y": 21
      }
    }
  },
  {
    "timestamp_ms": 2341,
    "action": {
      "SetBlocked": {
        "x": 34,
        "y": 22
      }
    }
  },
  {
    "timestamp_ms": 2358,
    "action": {
      "SetBlocked": {
        "x": 34,
        "y": 23
      }
    }
  },
  {
    "timestamp_ms": 2391,
    "action": {
      "SetBlocked": {
        "x": 34,
        "y": 24
      }
    }
  },
  {
    "timestamp_ms": 2474,
    "action": {
      "SetBlocked": {
        "x": 33,
        "y": 25
      }
    }
  },
  {
    "timestamp_ms": 2591,
    "action": {
      "SetBlocked": {
        "x": 32,
        "y": 25
      }
    }
  },
  {
    "timestamp_ms": 2607,
    "action": {
      "SetBlocked": {
        "x": 32,
        "y": 26
      }
    }
  },
  {
    "timestamp_ms": 2674,
    "action": {
      "SetBlocked": {
        "x": 31,
        "y": 26
      }
    }
  },
  {
    "timestamp_ms": 2724,
    "action": {
      "SetBlocked": {
        "x": 31,
        "y": 27
      }
    }
  },
  {
    "timestamp_ms": 2741,
    "action": {
      "SetBlocked": {
        "x": 31,
        "y": 28
      }
    }
  },
  {
    "timestamp_ms": 2774,
    "action": {
      "SetBlocked": {
        "x": 31,
        "y": 29
      }
    }
  },
  {
    "timestamp_ms": 2807,
    "action": {
      "SetBlocked": {
        "x": 30,
        "y": 30
      }
    }
  },
  {
    "timestamp_ms": 2874,
    "action": {
      "SetBlocked": {
        "x": 30,
        "y": 31
      }
    }
  },
  {
    "timestamp_ms": 2891,
    "action": {
      "SetBlocked": {
        "x": 29,
        "y": 31
      }
    }
  },
  {
    "timestamp_ms": 2974,
    "action": {
      "SetBlocked": {
        "x": 28,
        "y": 31
      }
    }
  },
  {
    "timestamp_ms": 3041,
    "action": {
      "SetBlocked": {
        "x": 27,
        "y": 31
      }
    }
  },
  {
    "timestamp_ms": 3091,
    "action": {
      "SetBlocked": {
        "x": 26,
        "y": 31
      }
    }
  },
  {
    "timestamp_ms": 3107,
    "action": {
      "SetBlocked": {
        "x": 25,
        "y": 31
      }
    }
  },
  {
    "timestamp_ms": 3124,
    "action": {
      "SetBlocked": {
        "x": 24,
        "y": 31
      }
    }
  },
  {
    "timestamp_ms": 3141,
    "action": {
      "SetBlocked": {
        "x": 23,
        "y": 31
      }
    }
  },
  {
    "timestamp_ms": 3257,
    "action": {
      "SetBlocked": {
        "x": 22,
        "y": 31
      }
    }
  },
  {
    "timestamp_ms": 3274,
    "action": {
      "SetBlocked": {
        "x": 21,
        "y": 30
      }
    }
  },
  {
    "timestamp_ms": 3307,
    "action": {
      "SetBlocked": {
        "x": 20,
        "y": 30
      }
    }
  },
  {
    "timestamp_ms": 3324,
    "action": {
      "SetBlocked": {
        "x": 20,
        "y": 29
      }
    }
  },
  {
    "timestamp_ms": 3374,
    "action": {
      "SetBlocked": {
        "x": 19,
        "y": 29
      }
    }
  },
  {
    "timestamp_ms": 3424,
    "action": {
      "SetBlocked": {
        "x": 18,
        "y": 29
      }
    }
  },
  {
    "timestamp_ms": 3441,
    "action": {
      "SetBlocked": {
        "x": 17,
        "y": 28
      }
    }
  },
  {
    "timestamp_ms": 3541,
    "action": {
      "SetBlocked": {
        "x": 16,
        "y": 28
      }
    }
  },
  {
    "timestamp_ms": 3674,
    "action": {
      "SetBlocked": {
        "x": 16,
        "y": 27
      }
    }
  },
  {
    "timestamp_ms": 3691,
    "action": {
      "SetBlocked": {
        "x": 15,
        "y": 25
      }
    }
  },
  {
    "timestamp_ms": 3707,
    "action": {
      "SetBlocked": {
        "x": 14,
        "y": 24
      }
    }
  },
  {
    "timestamp_ms": 3724,
    "action": {
      "SetBlocked": {
        "x": 14,
        "y": 23
      }
    }
  },
  {
    "timestamp_ms": 3891,
    "action": {
      "SetBlocked": {
        "x": 13,
        "y": 22
      }
    }
  },
  {
    "timestamp_ms": 3941,
    "action": {
      "SetBlocked": {
        "x": 13,
        "y": 21
      }
    }
  },
  {
    "timestamp_ms": 3957,
    "action": {
      "SetBlocked": {
        "x": 14,
        "y": 20
      }
    }
  },
  {
    "timestamp_ms": 4007,
    "action": {
      "SetBlocked": {
        "x": 14,
        "y": 19
      }
    }
  },
  {
    "timestamp_ms": 4024,
    "action": {
      "SetBlocked": {
        "x": 16,
        "y": 18
      }
    }
  },
  {
    "timestamp_ms": 4041,
    "action": {
      "SetBlocked": {
        "x": 17,
        "y": 18
      }
    }
  },
  {
    "timestamp_ms": 4074,
    "action": {
      "SetBlocked": {
        "x": 18,
        "y": 18
      }
    }
  },
  {
    "timestamp_ms": 4107,
    "action": {
      "SetBlocked": {
        "x": 19,
        "y": 17
      }
    }
  },
  {
    "timestamp_ms": 4124,
    "action": {
      "SetBlocked": {
        "x": 20,
        "y": 17
      }
    }
  },
  {
    "timestamp_ms": 4141,
    "action": {
      "SetBlocked": {
        "x": 21,
        "y": 16
      }
    }
  },
  {
    "timestamp_ms": 4158,
    "action": {
      "SetBlocked": {
        "x": 22,
        "y": 16
      }
    }
  },
  {
    "timestamp_ms": 4174,
    "action": {
      "SetBlocked": {
        "x": 24,
        "y": 16
      }
    }
  },
  {
    "timestamp_ms": 4307,
    "action": {
      "SetBlocked": {
        "x": 25,
        "y": 16
      }
    }
  },
  {
    "timestamp_ms": 4441,
    "action": {
      "SetBlocked": {
        "x": 26,
        "y": 17
      }
    }
  },
  {
    "timestamp_ms": 4457,
    "action": {
      "SetBlocked": {
        "x": 26,
        "y": 19
      }
    }
  },
  {
    "timestamp_ms": 4491,
    "action": {
      "SetBlocked": {
        "x": 27,
        "y": 20
      }
    }
  },
  {
    "timestamp_ms": 4507,
    "action": {
      "SetBlocked": {
        "x": 27,
        "y": 21
      }
    }
  },
  {
    "timestamp_ms": 4574,
    "action": {
      "SetBlocked": {
        "x": 27,
        "y": 22
      }
    }
  },
  {
    "timestamp_ms": 4591,
    "action": {
      "SetBlocked": {
        "x": 27,
        "y": 24
      }
    }
  },
  {
    "timestamp_ms": 4791,
    "action": {
      "SetBlocked": {
        "x": 26,
        "y": 24
      }
    }
  },
  {
    "timestamp_ms": 4841,
    "action": {
      "SetBlocked": {
        "x": 26,
        "y": 25
      }
    }
  },
  {
    "timestamp_ms": 4874,
    "action": {
      "SetBlocked": {
        "x": 25,
        "y": 24
      }
    }
  },
  {
    "timestamp_ms": 4907,
    "action": {
      "SetBlocked": {
        "x": 24,
        "y": 24
      }
    }
  },
  {
    "timestamp_ms": 5008,
    "action": {
      "SetBlocked": {
        "x": 23,
        "y": 24
      }
    }
  },
  {
    "timestamp_ms": 5141,
    "action": {
      "SetBlocked": {
        "x": 22,
        "y": 24
      }
    }
  },
  {
    "timestamp_ms": 5157,
    "action": {
      "SetBlocked": {
        "x": 21,
        "y": 24
      }
    }
  },
  {
    "timestamp_ms": 5308,
    "action": {
      "SetBlocked": {
        "x": 20,
        "y": 24
      }
    }
  },
  {
    "timestamp_ms": 5524,
    "action": {
      "SetBlocked": {
        "x": 19,
        "y": 24
      }
    }
  },
  {
    "timestamp_ms": 5541,
    "action": {
      "SetBlocked": {
        "x": 18,
        "y": 24
      }
    }
  },
  {
    "timestamp_ms": 5857,
    "action": {
      "SetBlocked": {
        "x": 17,
        "y": 24
      }
    }
  },
  {
    "timestamp_ms": 5874,
    "action": {
      "SetBlocked": {
        "x": 17,
        "y": 23
      }
    }
  },
  {
    "timestamp_ms": 7691,
    "action": {
      "SpawnActor": {
        "x": 142.0,
        "y": 553.0
      }
    }
  },
  {
    "timestamp_ms": 8291,
    "action": {
      "SpawnActor": {
        "x": 76.0,
        "y": 376.0
      }
    }
  },
  {
    "timestamp_ms": 8758,
    "action": {
      "SpawnActor": {
        "x": 127.0,
        "y": 152.0
      }
    }
  },
  {
    "timestamp_ms": 9541,
    "action": {
      "SpawnActor": {
        "x": 663.0,
        "y": 97.0
      }
    }
  },
  {
    "timestamp_ms": 10208,
    "action": {
      "SpawnActor": {
        "x": 715.0,
        "y": 457.0
      }
    }
  },
  {
    "timestamp_ms": 10741,
    "action": {
      "SpawnActor": {
        "x": 526.0,
        "y": 546.0
      }
    }
  },
  {
    "timestamp_ms": 14783,
    "action": {
      "SetActorDestination": {
        "x": 18,
        "y": 21,
        "actor_count": 6
      }
    }
  },
  {
    "timestamp_ms": 17309,
    "action": {
      "SetActorDestination": {
        "x": 37,
        "y": 37,
        "actor_count": 6
      }
    }
  },
  {
    "timestamp_ms": 20300,
    "action": {
      "SetActorDestination": {
        "x": 4,
        "y": 8,
        "actor_count": 6
      }
    }
  }
]